<?xml version="1.0" encoding="UTF-8"?>
<objects serializationModel="Studio.02.02.00">
	<object class="AudioFile" id="{ac7d929c-cd50-47f8-b00d-9763cac91a71}">
		<property name="assetPath">
			<value>Menu/Lv99Jam_giveAchieve2.wav</value>
		</property>
		<property name="frequencyInKHz">
			<value>48</value>
		</property>
		<property name="channelCount">
			<value>2</value>
		</property>
		<property name="length">
			<value>2.6121249999999998</value>
		</property>
		<relationship name="masterAssetFolder">
			<destination>{caf2f4fc-e9c4-486f-ad66-0338d34c7352}</destination>
		</relationship>
	</object>
</objects>
